langevals_azure/content_safety.py
langevals_azure/jailbreak.py
langevals_azure/prompt_injection.py
langevals_azure-0.1.14.dist-info/METADATA
langevals_azure-0.1.14.dist-info/WHEEL
langevals_azure-0.1.14.dist-info/RECORD
